matiCalpackage/__init__.py
matiCalpackage/add.py
matiCalpackage/subtract.py
matiCalpackage/extras/__init__.py
matiCalpackage/extras/divide.py
matiCalpackage/extras/multiply.py
matiCalpackage-0.0.5.dist-info/METADATA
matiCalpackage-0.0.5.dist-info/WHEEL
matiCalpackage-0.0.5.dist-info/top_level.txt
matiCalpackage-0.0.5.dist-info/RECORD
