Metadata-Version: 2.1
Name: matiCalpackage
Version: 0.0.5
Summary: My first Python package
Home-page: UNKNOWN
Author: Md Amjad Hossain
Author-email: <amjadkuet@gmail.com>
License: UNKNOWN
Keywords: python,simpleCalpackage
Platform: UNKNOWN
Classifier: Development Status :: 3 - Alpha
Classifier: Intended Audience :: Education
Classifier: Programming Language :: Python :: 2
Classifier: Programming Language :: Python :: 3
Classifier: Operating System :: MacOS :: MacOS X
Classifier: Operating System :: Microsoft :: Windows
